fafbseg/__init__.py
fafbseg/__version__.py
fafbseg/utils.py
fafbseg/data/JFRC2NP.surf.fw.zip
fafbseg/data/README.md
fafbseg/data/global_area_ids.npy.zip
fafbseg/data/ngl_scenes.json
fafbseg/data/volume_name_dict.json
fafbseg/flywire/__init__.py
fafbseg/flywire/_synapses_spine.py
fafbseg/flywire/annotations.py
fafbseg/flywire/l2.py
fafbseg/flywire/merge.py
fafbseg/flywire/meshes.py
fafbseg/flywire/neuroglancer.py
fafbseg/flywire/segmentation.py
fafbseg/flywire/skeletonize.py
fafbseg/flywire/synapses.py
fafbseg/flywire/utils.py
fafbseg/flywire/blender/__init__.py
fafbseg/flywire/blender/templates/blender_render.py.template
fafbseg/google/__init__.py
fafbseg/google/meshes.py
fafbseg/google/segmentation.py
fafbseg/google/synapses.py
fafbseg/move/__init__.py
fafbseg/move/interfaces.py
fafbseg/move/merge.py
fafbseg/move/merge_utils.py
fafbseg/spine/__init__.py
fafbseg/spine/base.py
fafbseg/synapses/__init__.py
fafbseg/synapses/offline.py
fafbseg/synapses/online.py
fafbseg/synapses/transmitters.py
fafbseg/synapses/utils.py
fafbseg/xform/__init__.py
fafbseg/xform/xform.py
fafbseg-3.2.0.dist-info/licenses/LICENSE
fafbseg-3.2.0.dist-info/METADATA
fafbseg-3.2.0.dist-info/WHEEL
fafbseg-3.2.0.dist-info/top_level.txt
fafbseg-3.2.0.dist-info/RECORD
