Metadata-Version: 2.4
Name: fafbseg
Version: 3.2.0
Summary: Tools to work with the FlyWire and Google segmentations of the FAFB EM dataset
Home-page: https://fafbseg-py.readthedocs.io
Author: Philipp Schlegel
Author-email: pms70@cam.ac.uk
License: GNU GPL V3
Project-URL: Documentation, https://fafbseg-py.readthedocs.io
Project-URL: Source, https://github.com/navis-org/fafbseg-py
Project-URL: Changelog, https://github.com/navis-org/fafbseg-py/releases
Keywords: FAFB neuron segmentation FlyWire Google synapses connectome fly brain navis CAVE
Classifier: Development Status :: 5 - Production/Stable
Classifier: Intended Audience :: Science/Research
Classifier: Topic :: Scientific/Engineering :: Bio-Informatics
Classifier: License :: OSI Approved :: GNU General Public License v3 or later (GPLv3+)
Classifier: Programming Language :: Python :: 3
Classifier: Programming Language :: Python :: 3.10
Classifier: Programming Language :: Python :: 3.11
Classifier: Programming Language :: Python :: 3.12
Classifier: Programming Language :: Python :: 3.13
Requires-Python: >=3.10
License-File: LICENSE
Requires-Dist: caveclient>=5.4.2
Requires-Dist: cloud-volume>=8.20
Requires-Dist: diskcache
Requires-Dist: fastremap
Requires-Dist: inquirer>=2.6
Requires-Dist: ipython
Requires-Dist: navis<2.0,>=1.8.0
Requires-Dist: numpy
Requires-Dist: pandas>=1.1.0
Requires-Dist: pyarrow>=3.0.0
Requires-Dist: pyperclip
Requires-Dist: python-catmaid>=2.0.2
Requires-Dist: requests
Requires-Dist: requests-futures
Requires-Dist: skeletor>=1.0.0
Requires-Dist: trimesh
Requires-Dist: tqdm
Requires-Dist: fuzzywuzzy
Dynamic: author
Dynamic: author-email
Dynamic: classifier
Dynamic: description
Dynamic: description-content-type
Dynamic: home-page
Dynamic: keywords
Dynamic: license
Dynamic: license-file
Dynamic: project-url
Dynamic: requires-dist
Dynamic: requires-python
Dynamic: summary
